{
  "data": [
    {
      "institutionsName": "佳一教育",
      "teacherName": "小丁教师383",
      "evalPerson": 104,
      "campusesName": "北京懒洋洋婴幼儿英语教育",
      "courseId": 55700979,
      "teacher_id": "17055707",
      "course_id": "35963690",
      "teacher_actor": "1_tpl_96.jpg",
      "name": "体操一班",
      "class_time_names": "09:30-10:30",
      "address": "北京市海淀区西北旺中关村科技园1",
      "district": "海淀区",
      "browse_number": 132,
      "lesson_total": 12,
      "cost": 2001,
      "mall_cost": 2001,
      "person": "钢琴基础",
      "goods_week": "3-5@3-7",
      "is_openClass": "2",
      "is_discount": "2",
      "is_groupPurchase": "2",
      "is_discountRate": "1",
      "is_minus": "1",
      "is_detailTime": "2",
      "is_audition": "1",
      "is_transfer": "2",
      "is_free": "1",
      "is_signup": "2",
      "is_enforce": "3",
      "retreat_rule": "1",
      "total": 80,
      "saled": 43,
      "open_date": "2017-02-21T16:00:00.000Z",
      "end_date": "2017-08-08T16:00:00.000Z",
      "open_date1": "2017-02-22",
      "end_date1": "2017-08-09"
    },
    {
      "institutionsName": "佳一教育",
      "teacherName": "米伦1",
      "evalPerson": 104,
      "campusesName": "撒地方",
      "courseId": 55701089,
      "teacher_id": "17055705",
      "course_id": "35963690",
      "teacher_actor": "1_tpl_13.jpg",
      "name": "体操SQFX--007",
      "class_time_names": "09:30-10:30",
      "address": "北京市海淀区西北旺中关村科技园1",
      "district": "海淀区",
      "browse_number": 132,
      "lesson_total": 12,
      "cost": 1500,
      "mall_cost": 1500,
      "person": "钢琴基础",
      "goods_week": "3-5@3-6@3-7",
      "is_openClass": "1",
      "is_discount": "2",
      "is_groupPurchase": "2",
      "is_discountRate": "2",
      "is_minus": "2",
      "is_detailTime": "3",
      "is_audition": "1",
      "is_transfer": "2",
      "is_free": "1",
      "is_signup": "2",
      "is_enforce": "3",
      "retreat_rule": "1",
      "total": 80,
      "saled": 43,
      "open_date": "2017-02-02T16:00:00.000Z",
      "end_date": "2017-08-08T16:00:00.000Z",
      "open_date1": "2017-02-03",
      "end_date1": "2017-08-09"
    },
    {
      "institutionsName": "佳一教育",
      "teacherName": "李季",
      "evalPerson": 104,
      "campusesName": "西城校区",
      "courseId": 55700879,
      "teacher_id": "17055718",
      "course_id": "35963690",
      "teacher_actor": "1_tpl_95.jpg",
      "name": "体操b教室",
      "class_time_names": "09:30-10:30",
      "address": "北京市海淀区西北旺中关村科技园1",
      "district": "海淀区",
      "browse_number": 132,
      "lesson_total": 12,
      "cost": 1000,
      "mall_cost": 1000,
      "person": "钢琴基础",
      "goods_week": "3-5@3-7",
      "is_openClass": "2",
      "is_discount": "2",
      "is_groupPurchase": "2",
      "is_discountRate": "1",
      "is_minus": "1",
      "is_detailTime": "2",
      "is_audition": "1",
      "is_transfer": "2",
      "is_free": "1",
      "is_signup": "2",
      "is_enforce": "2",
      "retreat_rule": "1",
      "total": 90,
      "saled": 56,
      "open_date": "2016-01-06T16:00:00.000Z",
      "end_date": "2017-08-08T16:00:00.000Z",
      "open_date1": "2016-01-07",
      "end_date1": "2017-08-09"
    },
    {
      "institutionsName": "校管家教育",
      "teacherName": "米伦1",
      "evalPerson": 104,
      "campusesName": "魏公村分校",
      "courseId": 55702400,
      "teacher_id": "17056291",
      "course_id": "35963690",
      "teacher_actor": "1_tpl_75.jpg",
      "name": "体操--007",
      "class_time_names": "09:30-10:30",
      "address": "北京市海淀区西北旺中关村科技园1",
      "district": "海淀区",
      "browse_number": 132,
      "lesson_total": 12,
      "cost": 500,
      "mall_cost": 500,
      "person": "钢琴基础",
      "goods_week": "3-7",
      "is_openClass": "2",
      "is_discount": "2",
      "is_groupPurchase": "2",
      "is_discountRate": "1",
      "is_minus": "1",
      "is_detailTime": "1",
      "is_audition": "2",
      "is_transfer": "1",
      "is_free": "1",
      "is_signup": "1",
      "is_enforce": "2",
      "retreat_rule": "1",
      "total": 36,
      "saled": 9,
      "open_date": "2017-01-08T16:00:00.000Z",
      "end_date": "2017-01-21T16:00:00.000Z",
      "open_date1": "2017-01-09",
      "end_date1": "2017-01-22"
    },
    {
      "institutionsName": "爱校教育",
      "teacherName": "米伦1",
      "evalPerson": 104,
      "campusesName": "河北医科大学",
      "courseId": 55702216,
      "teacher_id": "17056186",
      "course_id": "35963690",
      "teacher_actor": "1_tpl_83.jpg",
      "name": "体操1",
      "class_time_names": "09:30-10:30",
      "address": "北京市海淀区西北旺中关村科技园1",
      "district": "海淀区",
      "browse_number": 132,
      "lesson_total": 12,
      "cost": 500,
      "mall_cost": 500,
      "person": "钢琴基础",
      "goods_week": "3-2@3-3@3-4@3-5@3-6",
      "is_openClass": "1",
      "is_discount": "1",
      "is_groupPurchase": "1",
      "is_discountRate": "2",
      "is_minus": "1",
      "is_detailTime": "2",
      "is_audition": "1",
      "is_transfer": "2",
      "is_free": "1",
      "is_signup": "1",
      "is_enforce": "3",
      "retreat_rule": "2",
      "total": 68,
      "saled": 45,
      "open_date": "2015-06-03T16:00:00.000Z",
      "end_date": "2017-08-08T16:00:00.000Z",
      "open_date1": "2015-06-04",
      "end_date1": "2017-08-09"
    },
    {
      "institutionsName": "佳一教育",
      "teacherName": "李季",
      "evalPerson": 104,
      "campusesName": "北京懒洋洋婴幼儿英语教育",
      "courseId": 55700814,
      "teacher_id": "17055709",
      "course_id": "35963690",
      "teacher_actor": "1_tpl_20.jpg",
      "name": "体操QFX--007",
      "class_time_names": "09:30-10:30",
      "address": "北京市海淀区西北旺中关村科技园1",
      "district": "海淀区",
      "browse_number": 132,
      "lesson_total": 12,
      "cost": 200,
      "mall_cost": 200,
      "person": "钢琴基础",
      "goods_week": "3-2@3-3",
      "is_openClass": "1",
      "is_discount": "1",
      "is_groupPurchase": "1",
      "is_discountRate": "1",
      "is_minus": "2",
      "is_detailTime": "3",
      "is_audition": "1",
      "is_transfer": "1",
      "is_free": "1",
      "is_signup": "2",
      "is_enforce": "2",
      "retreat_rule": "1",
      "total": 90,
      "saled": 56,
      "open_date": "2016-02-05T16:00:00.000Z",
      "end_date": "2017-08-08T16:00:00.000Z",
      "open_date1": "2016-02-06",
      "end_date1": "2017-08-09"
    },
    {
      "institutionsName": "佳一教育",
      "teacherName": "米伦1",
      "evalPerson": 104,
      "campusesName": "新西兰分校",
      "courseId": 55700752,
      "teacher_id": "17055732",
      "course_id": "35963690",
      "teacher_actor": "1_tpl_61.jpg",
      "name": "体操WGCFX--003",
      "class_time_names": "09:30-10:30",
      "address": "北京市海淀区西北旺中关村科技园1",
      "district": "海淀区",
      "browse_number": 132,
      "lesson_total": 12,
      "cost": 100,
      "mall_cost": 100,
      "person": "钢琴基础",
      "goods_week": "3-2@3-3",
      "is_openClass": "1",
      "is_discount": "1",
      "is_groupPurchase": "1",
      "is_discountRate": "1",
      "is_minus": "2",
      "is_detailTime": "3",
      "is_audition": "1",
      "is_transfer": "1",
      "is_free": "1",
      "is_signup": "2",
      "is_enforce": "2",
      "retreat_rule": "1",
      "total": 90,
      "saled": 56,
      "open_date": "2017-05-27T16:00:00.000Z",
      "end_date": "2017-06-24T16:00:00.000Z",
      "open_date1": "2017-05-28",
      "end_date1": "2017-06-25"
    },
    {
      "institutionsName": "佳一教育",
      "teacherName": "艺术2班",
      "evalPerson": 104,
      "campusesName": "西城校区",
      "courseId": 55700693,
      "teacher_id": "17055712",
      "course_id": "35963690",
      "teacher_actor": "1_tpl_02.jpg",
      "name": "体操LSQFX--007",
      "class_time_names": "09:30-10:30",
      "address": "北京市海淀区西北旺中关村科技园1",
      "district": "海淀区",
      "browse_number": 132,
      "lesson_total": 12,
      "cost": 100,
      "mall_cost": 100,
      "person": "钢琴基础",
      "goods_week": "3-2@3-3",
      "is_openClass": "1",
      "is_discount": "1",
      "is_groupPurchase": "1",
      "is_discountRate": "1",
      "is_minus": "2",
      "is_detailTime": "3",
      "is_audition": "1",
      "is_transfer": "1",
      "is_free": "1",
      "is_signup": "2",
      "is_enforce": "3",
      "retreat_rule": "1",
      "total": 90,
      "saled": 56,
      "open_date": "2016-06-19T16:00:00.000Z",
      "end_date": "2016-07-08T16:00:00.000Z",
      "open_date1": "2016-06-20",
      "end_date1": "2016-07-09"
    },
    {
      "institutionsName": "佳一教育",
      "teacherName": "米伦1",
      "evalPerson": 104,
      "campusesName": "新西兰分校",
      "courseId": 55701732,
      "teacher_id": "17055731",
      "course_id": "35963690",
      "teacher_actor": "1_tpl_78.jpg",
      "name": "体操乐LSQFX--007",
      "class_time_names": "09:30-10:30",
      "address": "北京市海淀区西北旺中关村科技园1",
      "district": "海淀区",
      "browse_number": 132,
      "lesson_total": 12,
      "cost": 100,
      "mall_cost": 100,
      "person": "钢琴基础",
      "goods_week": "3-4@3-5@3-7",
      "is_openClass": "2",
      "is_discount": "2",
      "is_groupPurchase": "2",
      "is_discountRate": "1",
      "is_minus": "2",
      "is_detailTime": "3",
      "is_audition": "1",
      "is_transfer": "2",
      "is_free": "1",
      "is_signup": "2",
      "is_enforce": "3",
      "retreat_rule": "2",
      "total": 60,
      "saled": 0,
      "open_date": "2016-06-30T16:00:00.000Z",
      "end_date": "2016-08-03T16:00:00.000Z",
      "open_date1": "2016-07-01",
      "end_date1": "2016-08-04"
    },
    {
      "institutionsName": "佳一教育",
      "teacherName": "艺术2班",
      "evalPerson": 104,
      "campusesName": "西城校区",
      "courseId": 55700900,
      "teacher_id": "17055712",
      "course_id": "35963690",
      "teacher_actor": "1_tpl_17.jpg",
      "name": "体操教室",
      "class_time_names": "09:30-10:30",
      "address": "北京市海淀区西北旺中关村科技园1",
      "district": "海淀区",
      "browse_number": 132,
      "lesson_total": 12,
      "cost": 60,
      "mall_cost": 60,
      "person": "钢琴基础",
      "goods_week": "3-5@3-7",
      "is_openClass": "2",
      "is_discount": "2",
      "is_groupPurchase": "2",
      "is_discountRate": "1",
      "is_minus": "1",
      "is_detailTime": "2",
      "is_audition": "1",
      "is_transfer": "2",
      "is_free": "1",
      "is_signup": "2",
      "is_enforce": "2",
      "retreat_rule": "1",
      "total": 90,
      "saled": 56,
      "open_date": "2017-03-12T16:00:00.000Z",
      "end_date": "2017-08-08T16:00:00.000Z",
      "open_date1": "2017-03-13",
      "end_date1": "2017-08-09"
    },
    {
      "institutionsName": "佳一教育",
      "teacherName": "赵老师",
      "evalPerson": 104,
      "campusesName": "西城校区",
      "courseId": 55701430,
      "teacher_id": "17055715",
      "course_id": "35963690",
      "teacher_actor": "1_tpl_67.jpg",
      "name": "体操教室",
      "class_time_names": "09:30-10:30",
      "address": "北京市海淀区西北旺中关村科技园1",
      "district": "海淀区",
      "browse_number": 132,
      "lesson_total": 12,
      "cost": 60,
      "mall_cost": 60,
      "person": "钢琴基础",
      "goods_week": "3-1@3-2@3-3@3-4@3-5",
      "is_openClass": "1",
      "is_discount": "1",
      "is_groupPurchase": "1",
      "is_discountRate": "2",
      "is_minus": "1",
      "is_detailTime": "3",
      "is_audition": "2",
      "is_transfer": "1",
      "is_free": "2",
      "is_signup": "1",
      "is_enforce": "1",
      "retreat_rule": "1",
      "total": 80,
      "saled": 43,
      "open_date": "2016-03-06T16:00:00.000Z",
      "end_date": "2017-08-08T16:00:00.000Z",
      "open_date1": "2016-03-07",
      "end_date1": "2017-08-09"
    },
    {
      "institutionsName": "爱斯创",
      "teacherName": "高王玉",
      "evalPerson": 104,
      "campusesName": "北京航空大学",
      "courseId": 55702034,
      "teacher_id": "17056004",
      "course_id": "35963690",
      "teacher_actor": "1_tpl_94.jpg",
      "name": "体操试D353班",
      "class_time_names": "09:30-10:30",
      "address": "北京市海淀区西北旺中关村科技园1",
      "district": "海淀区",
      "browse_number": 132,
      "lesson_total": 12,
      "cost": 0,
      "mall_cost": 0,
      "person": "钢琴基础",
      "goods_week": "3-2@3-3@3-4@3-5@3-6",
      "is_openClass": "1",
      "is_discount": "1",
      "is_groupPurchase": "1",
      "is_discountRate": "2",
      "is_minus": "1",
      "is_detailTime": "2",
      "is_audition": "2",
      "is_transfer": "1",
      "is_free": "1",
      "is_signup": "2",
      "is_enforce": "1",
      "retreat_rule": "1",
      "total": 68,
      "saled": 45,
      "open_date": "2017-03-12T16:00:00.000Z",
      "end_date": "2017-08-08T16:00:00.000Z",
      "open_date1": "2017-03-13",
      "end_date1": "2017-08-09"
    }
  ],
  "offset": "0"
}